[
  {
    "name": "ARANA RODRIGUEZ MARÍA CAMILA",
    "curso": "7A",
    "puntos": 0
  },
  {
    "name": "ARANGO NAVARRO EMILIE ALEXA",
    "curso": "7A",
    "puntos": 0
  },
  {
    "name": "ARIZA AGUILLON NICHOLAS",
    "curso": "7A",
    "puntos": 0
  },
  {
    "name": "CABALLERO SOTO CHRISTOPHER KEILET",
    "curso": "7A",
    "puntos": 0
  },
  {
    "name": "CABARCAS DIAZ GUSTAVO MIGUEL",
    "curso": "7A",
    "puntos": 0
  },
  {
    "name": "CAMARGO PINZON JERONIMO",
    "curso": "7A",
    "puntos": 0
  },
  {
    "name": "FORERO ESTUPIÑAN THOMAS PHILIPPE",
    "curso": "7A",
    "puntos": 0
  },
  {
    "name": "GARCES ARDILA OSCAR JULIAN",
    "curso": "7A",
    "puntos": 0
  },
  {
    "name": "JIMENEZ AVILA JUAN JOSE",
    "curso": "7A",
    "puntos": 0
  },
  {
    "name": "LOPEZ ORTEGA MARIANA",
    "curso": "7A",
    "puntos": 0
  },
  {
    "name": "MAESTRE ROJAS JOSE EDUARDO",
    "curso": "7A",
    "puntos": 0
  },
  {
    "name": "MARTINEZ MUÑOZ SARAH NICOLL",
    "curso": "7A",
    "puntos": 0
  },
  {
    "name": "MEJIA NAJERA SILVANA",
    "curso": "7A",
    "puntos": 0
  },
  {
    "name": "MOLANO JIMENEZ VALERIA",
    "curso": "7A",
    "puntos": 0
  },
  {
    "name": "MORENO GONZALEZ KAMILA",
    "curso": "7A",
    "puntos": 0
  },
  {
    "name": "MOYA LONDOÑO SOFIA",
    "curso": "7A",
    "puntos": 0
  },
  {
    "name": "NOVA SAAVEDRA SAMANTHA",
    "curso": "7A",
    "puntos": 0
  },
  {
    "name": "PUERTO PEREZ NATALY SOFIA",
    "curso": "7A",
    "puntos": 0
  },
  {
    "name": "QUICENO CAÑON OSCAR DANIEL",
    "curso": "7A",
    "puntos": 0
  },
  {
    "name": "RAMIREZ GALINDO DANIEL FELIPE",
    "curso": "7A",
    "puntos": 0
  },
  {
    "name": "RAMIREZ MERCHAN SOFIA",
    "curso": "7A",
    "puntos": 0
  },
  {
    "name": "RICO LINARES EMILY SOFIA",
    "curso": "7A",
    "puntos": 0
  },
  {
    "name": "RIVERA CALDERIN THOMAS",
    "curso": "7A",
    "puntos": 0
  },
  {
    "name": "RODRIGUEZ PEREZ JUAN JOSE",
    "curso": "7A",
    "puntos": 0
  },
  {
    "name": "ROMERO SIERRA ISABELLA",
    "curso": "7A",
    "puntos": 0
  },
  {
    "name": "TRIVIÑO PRADA JULIAN DAVID",
    "curso": "7A",
    "puntos": 0
  },
  {
    "name": "VACCA PERILLA DIEGO ALEJANDRO",
    "curso": "7A",
    "puntos": 0
  },
  {
    "name": "ANGEL FABREGAS LUKAS",
    "curso": "7B",
    "puntos": 0
  },
  {
    "name": "BONILLA NAVARRETE MARIANA",
    "curso": "7B",
    "puntos": 0
  },
  {
    "name": "CARDOZO ROSADO SAMUEL ALEJANDRO",
    "curso": "7B",
    "puntos": 0
  },
  {
    "name": "CASTELLANOS MORALES ESTHER GABRIELA",
    "curso": "7B",
    "puntos": 0
  },
  {
    "name": "CHARRY QUINTERO MATTHEW ANTOINE",
    "curso": "7B",
    "puntos": 0
  },
  {
    "name": "CUERVO BELTRAN LUNA ISABELLA",
    "curso": "7B",
    "puntos": 0
  },
  {
    "name": "DIAZ GALINDO SAMUEL DAVID",
    "curso": "7B",
    "puntos": 0
  },
  {
    "name": "DIAZ PALENCIA SANTIAGO",
    "curso": "7B",
    "puntos": 0
  },
  {
    "name": "DUQUE BLANDON SERGIO",
    "curso": "7B",
    "puntos": 0
  },
  {
    "name": "FRESNO RIAÑO JUAN MANUEL",
    "curso": "7B",
    "puntos": 0
  },
  {
    "name": "GAÑAN GUTIERREZ MARTIN",
    "curso": "7B",
    "puntos": 0
  },
  {
    "name": "GAYOZO GARAY GABRIEL ENRIQUE",
    "curso": "7B",
    "puntos": 0
  },
  {
    "name": "MANTILLA JIMENEZ DANA LUCIA",
    "curso": "7B",
    "puntos": 0
  },
  {
    "name": "MORAN SANCHEZ GABRIELA",
    "curso": "7B",
    "puntos": 0
  },
  {
    "name": "PEÑA GONZALEZ STIVEN ALFONSO",
    "curso": "7B",
    "puntos": 0
  },
  {
    "name": "PINILLOS SUAREZ JUAN NICOLAS",
    "curso": "7B",
    "puntos": 0
  },
  {
    "name": "PISCIOTTI GOMEZ MARIANA",
    "curso": "7B",
    "puntos": 0
  },
  {
    "name": "RINCON MACIAS TOMAS DAVID",
    "curso": "7B",
    "puntos": 0
  },
  {
    "name": "RIVERA PALACIO TOMAS SANTIAGO",
    "curso": "7B",
    "puntos": 0
  },
  {
    "name": "RUIZ SALAZAR GABRIELA ALEJANDRA",
    "curso": "7B",
    "puntos": 0
  },
  {
    "name": "SILVA OSPINA ANNIE GABRIELA",
    "curso": "7B",
    "puntos": 0
  },
  {
    "name": "SUAREZ ARIAS ISABELLA",
    "curso": "7B",
    "puntos": 0
  },
  {
    "name": "TIQUE VARGAS SARA SOFIA",
    "curso": "7B",
    "puntos": 0
  },
  {
    "name": "TORO SAIZ JUAN FELIPE",
    "curso": "7B",
    "puntos": 0
  },
  {
    "name": "TORRES CABEZAS JERONIMO",
    "curso": "7B",
    "puntos": 0
  },
  {
    "name": "TORRES CAMPOS VALERY SOFIA",
    "curso": "7B",
    "puntos": 0
  },
  {
    "name": "ACOSTA ROJAS MARIA PAULA",
    "curso": "7C",
    "puntos": 0
  },
  {
    "name": "AGUDELO GIRALDO MARIA PAULA",
    "curso": "7C",
    "puntos": 0
  },
  {
    "name": "BALLEN MANCILLA MARIA JOSE",
    "curso": "7C",
    "puntos": 0
  },
  {
    "name": "BARRERA RODRIGUEZ JORGE ANDRES",
    "curso": "7C",
    "puntos": 0
  },
  {
    "name": "BONILLA MENDOZA LAURA JIMENA",
    "curso": "7C",
    "puntos": 0
  },
  {
    "name": "CAICEDO COLORADO ANA ISABELLA",
    "curso": "7C",
    "puntos": 0
  },
  {
    "name": "CHALA RIZO SANTIAGO",
    "curso": "7C",
    "puntos": 0
  },
  {
    "name": "CHAVEZ SOTELO LUIS DAVID",
    "curso": "7C",
    "puntos": 0
  },
  {
    "name": "DEMOYA CADENA NICOLAS",
    "curso": "7C",
    "puntos": 0
  },
  {
    "name": "ESCOBAR CHIPATECUA ANTONELLA",
    "curso": "7C",
    "puntos": 0
  },
  {
    "name": "ESCOBAR CHIPATECUA ISABELLA",
    "curso": "7C",
    "puntos": 0
  },
  {
    "name": "ESLAVA TELLO MIGUEL ANGEL",
    "curso": "7C",
    "puntos": 0
  },
  {
    "name": "GALINDO NEME SAMUEL DAVID",
    "curso": "7C",
    "puntos": 0
  },
  {
    "name": "GUTIERREZ PRIETO JUAN FELIPE",
    "curso": "7C",
    "puntos": 0
  },
  {
    "name": "GUZMAN SANCHEZ SOFIA",
    "curso": "7C",
    "puntos": 0
  },
  {
    "name": "MARTINEZ SANTANA ISABELLA",
    "curso": "7C",
    "puntos": 0
  },
  {
    "name": "MILLAN TAMAYO MARIA JOSE",
    "curso": "7C",
    "puntos": 0
  },
  {
    "name": "NIÑO BARRERA SAMUEL ALEJANDRO",
    "curso": "7C",
    "puntos": 0
  },
  {
    "name": "ORTEGON MOYA ALEJANDRO",
    "curso": "7C",
    "puntos": 0
  },
  {
    "name": "RIVERA TORRES MARTIN",
    "curso": "7C",
    "puntos": 0
  },
  {
    "name": "ROA CUERVO JUAN DAVID",
    "curso": "7C",
    "puntos": 0
  },
  {
    "name": "RUGE CARVAJAL VALERY SAMANTA",
    "curso": "7C",
    "puntos": 0
  },
  {
    "name": "URDINOLA VARGAS ISABELLA",
    "curso": "7C",
    "puntos": 0
  },
  {
    "name": "VALBUENA ESPINDOLA ISABELLA",
    "curso": "7C",
    "puntos": 0
  },
  {
    "name": "VELEZ POVEDA SAMUEL CAMILO",
    "curso": "7C",
    "puntos": 0
  },
  {
    "name": "ZAMORA RODRIGUEZ MARIACAMILA",
    "curso": "7C",
    "puntos": 0
  },
  {
    "name": "ALCAZAR ALBA JUAN ESTEBAN",
    "curso": "8A",
    "puntos": 0
  },
  {
    "name": "ALMANZA RAIGOSA SAMANTA ISABELA",
    "curso": "8A",
    "puntos": 0
  },
  {
    "name": "ALZA ERAZO MARIANA",
    "curso": "8A",
    "puntos": 0
  },
  {
    "name": "ANGEL GUZMAN CRISTHOPHER",
    "curso": "8A",
    "puntos": 0
  },
  {
    "name": "BAUTISTA MONTEALEGRE BRAYAN ANDRES",
    "curso": "8A",
    "puntos": 0
  },
  {
    "name": "BOHORQUEZ GIRALDO MARIA ALEJANDRA",
    "curso": "8A",
    "puntos": 0
  },
  {
    "name": "CAICEDO HERNANDEZ JERONIMO",
    "curso": "8A",
    "puntos": 0
  },
  {
    "name": "COY BARRIOS EMILY",
    "curso": "8A",
    "puntos": 0
  },
  {
    "name": "DELGADO SANCHEZ SAMUEL",
    "curso": "8A",
    "puntos": 0
  },
  {
    "name": "DIAZ GARZON SEBASTIAN",
    "curso": "8A",
    "puntos": 0
  },
  {
    "name": "DUARTE RIAÑO PAULA DANIELA",
    "curso": "8A",
    "puntos": 0
  },
  {
    "name": "FERNANDEZ PEÑA LUISA FERNANDA",
    "curso": "8A",
    "puntos": 0
  },
  {
    "name": "GAMBOA PEÑA DANNA JIMENA",
    "curso": "8A",
    "puntos": 0
  },
  {
    "name": "GARCIA ROMERO EMILY SOPHIA",
    "curso": "8A",
    "puntos": 0
  },
  {
    "name": "GARCIA SALINAS MARIA JOSE",
    "curso": "8A",
    "puntos": 0
  },
  {
    "name": "GOMEZ LOZANO JUANITA",
    "curso": "8A",
    "puntos": 0
  },
  {
    "name": "GONZALEZ PARRA ALICE MICHELLE",
    "curso": "8A",
    "puntos": 0
  },
  {
    "name": "GUTIERREZ BERNAL JERONIMO",
    "curso": "8A",
    "puntos": 0
  },
  {
    "name": "LARROTTA BARRERA ISABELLA",
    "curso": "8A",
    "puntos": 0
  },
  {
    "name": "LIZARAZO CAMACHO CRISTIAN EMMANUEL",
    "curso": "8A",
    "puntos": 0
  },
  {
    "name": "MEDELLIN IDROBO DANNA ISABELLA",
    "curso": "8A",
    "puntos": 0
  },
  {
    "name": "MENESES HINCAPIE ISABELLA",
    "curso": "8A",
    "puntos": 0
  },
  {
    "name": "MOYANO BELTRAN MIGUEL ANGEL",
    "curso": "8A",
    "puntos": 0
  },
  {
    "name": "PAJARO SANCHEZ ESTEBAN CAMILO",
    "curso": "8A",
    "puntos": 0
  },
  {
    "name": "PRADA CERON TOMAS",
    "curso": "8A",
    "puntos": 0
  },
  {
    "name": "PULIDO SANCHEZ MARIA ALEJANDRA",
    "curso": "8A",
    "puntos": 0
  },
  {
    "name": "RAMIREZ SANCHEZ JUAN SEBASTIAN",
    "curso": "8A",
    "puntos": 0
  },
  {
    "name": "REINA SEPULVEDA JUAN SEBASTIAN",
    "curso": "8A",
    "puntos": 0
  },
  {
    "name": "RODRIGUEZ CARO SARA GABRIELA",
    "curso": "8A",
    "puntos": 0
  },
  {
    "name": "ROJAS DIAZ MATIAS",
    "curso": "8A",
    "puntos": 0
  },
  {
    "name": "ROMERO CRUZ JUAN PABLO",
    "curso": "8A",
    "puntos": 0
  },
  {
    "name": "ROMERO MUÑOZ DANNA ISABELLA",
    "curso": "8A",
    "puntos": 0
  },
  {
    "name": "VARGAS RIVERA JUAN DIEGO",
    "curso": "8A",
    "puntos": 0
  },
  {
    "name": "VELASQUEZ URECHE ISABELLA",
    "curso": "8A",
    "puntos": 0
  },
  {
    "name": "ZUÑIGA LEON LAURA SOFIA",
    "curso": "8A",
    "puntos": 0
  },
  {
    "name": "AHUMADA GUIO ISABELA",
    "curso": "8B",
    "puntos": 0
  },
  {
    "name": "BERNAL MOSQUERA MARIANNA",
    "curso": "8B",
    "puntos": 0
  },
  {
    "name": "BULLA LOPEZ ANDERSON DAVID",
    "curso": "8B",
    "puntos": 0
  },
  {
    "name": "CAMACHO JAUREGUI GABRIELA",
    "curso": "8B",
    "puntos": 0
  },
  {
    "name": "CAMARGO QUINTERO GABRIEL ISAAC",
    "curso": "8B",
    "puntos": 0
  },
  {
    "name": "CARDENAS MANTILLA JUAN JOSE",
    "curso": "8B",
    "puntos": 0
  },
  {
    "name": "CASSIANI ROMERO SAMUEL MATIAS",
    "curso": "8B",
    "puntos": 0
  },
  {
    "name": "CLAVIJO MONTAÑO DYLAN NIKOLAS",
    "curso": "8B",
    "puntos": 0
  },
  {
    "name": "COY BARRIOS AMY",
    "curso": "8B",
    "puntos": 0
  },
  {
    "name": "FAJARDO CASTILLO ISABEL SOFIA",
    "curso": "8B",
    "puntos": 0
  },
  {
    "name": "GAMBOA NAVARRO KENNIER JOSUE",
    "curso": "8B",
    "puntos": 0
  },
  {
    "name": "GARAVITO TOVAR SANTIAGO ALEJANDRO",
    "curso": "8B",
    "puntos": 0
  },
  {
    "name": "GARCIA BARON SARA SOFIA",
    "curso": "8B",
    "puntos": 0
  },
  {
    "name": "GIRALDO VARGAS LUIS MARIO",
    "curso": "8B",
    "puntos": 0
  },
  {
    "name": "GOMEZ MORA OSCAR EDUARDO",
    "curso": "8B",
    "puntos": 0
  },
  {
    "name": "JARA TOVAR NICOLAS",
    "curso": "8B",
    "puntos": 0
  },
  {
    "name": "JIMENEZ AVILA ISABEL SOFIA",
    "curso": "8B",
    "puntos": 0
  },
  {
    "name": "MONTAÑA DIAZ JUAN SEBASTIAN",
    "curso": "8B",
    "puntos": 0
  },
  {
    "name": "MORENO PARRA JUAN JOSE",
    "curso": "8B",
    "puntos": 0
  },
  {
    "name": "MUNAR RODRIGUEZ JUAN SEBASTIAN",
    "curso": "8B",
    "puntos": 0
  },
  {
    "name": "MUÑOZ AVILES ESTEBAN ALEJANDRO",
    "curso": "8B",
    "puntos": 0
  },
  {
    "name": "OLAYA URBINA MARIA PAULA",
    "curso": "8B",
    "puntos": 0
  },
  {
    "name": "PARDO NARANJO DANIELA",
    "curso": "8B",
    "puntos": 0
  },
  {
    "name": "PARRA MELO BRENDA",
    "curso": "8B",
    "puntos": 0
  },
  {
    "name": "PARRA MENDEZ KEVIN SANTIAGO",
    "curso": "8B",
    "puntos": 0
  },
  {
    "name": "PEREZ GONZALEZ KATALINA",
    "curso": "8B",
    "puntos": 0
  },
  {
    "name": "RAMIREZ RINCON LAURA ISABELLA",
    "curso": "8B",
    "puntos": 0
  },
  {
    "name": "RICO PABON SARA",
    "curso": "8B",
    "puntos": 0
  },
  {
    "name": "ROA RODRIGUEZ ALAN RODRIGO",
    "curso": "8B",
    "puntos": 0
  },
  {
    "name": "ROMERO PACHON VALERIA",
    "curso": "8B",
    "puntos": 0
  },
  {
    "name": "SANCHEZ PINZON JERONIMO",
    "curso": "8B",
    "puntos": 0
  },
  {
    "name": "SANJUAN GUZMAN VALERIE",
    "curso": "8B",
    "puntos": 0
  },
  {
    "name": "SANJUANELO ALANDETE BENJAMÍN",
    "curso": "8B",
    "puntos": 0
  },
  {
    "name": "TALERO CASTAÑEDA SANTIAGO",
    "curso": "8B",
    "puntos": 0
  },
  {
    "name": "ZORRO ALZA JUAN PABLO",
    "curso": "8B",
    "puntos": 0
  },
  {
    "name": "ZULUAGA MARTINEZ SARA VALENTINA",
    "curso": "8B",
    "puntos": 0
  },
  {
    "name": "ACEVEDO OLIVERA NICOLAS",
    "curso": "9A",
    "puntos": 0
  },
  {
    "name": "BELLONI GARCIA ADRIANA VALENTINA",
    "curso": "9A",
    "puntos": 0
  },
  {
    "name": "BENAVIDES ALVAREZ LAURA DANIELA",
    "curso": "9A",
    "puntos": 0
  },
  {
    "name": "BENAVIDES CRUZ GABRIELA",
    "curso": "9A",
    "puntos": 0
  },
  {
    "name": "BOLIVAR GARCIA MARIA FERNANDA",
    "curso": "9A",
    "puntos": 0
  },
  {
    "name": "CASALLAS BENAVIDES DANA GABRIELA",
    "curso": "9A",
    "puntos": 0
  },
  {
    "name": "CASTRO RODRIGUEZ ANA MARIA",
    "curso": "9A",
    "puntos": 0
  },
  {
    "name": "CELIS GONZALEZ FRANCES GABRIELA",
    "curso": "9A",
    "puntos": 0
  },
  {
    "name": "IDARRAGA ACOSTA DANNA SOFIA",
    "curso": "9A",
    "puntos": 0
  },
  {
    "name": "IZQUIERDO ROA LESLY ISABELLA",
    "curso": "9A",
    "puntos": 0
  },
  {
    "name": "LARA ESPINOSA EMILY SHAININ",
    "curso": "9A",
    "puntos": 0
  },
  {
    "name": "MARTINEZ GALVIS MARIANA",
    "curso": "9A",
    "puntos": 0
  },
  {
    "name": "MEDINA ABRIL ANDRES DAVID",
    "curso": "9A",
    "puntos": 0
  },
  {
    "name": "MEJIA ANDRADE MARTIN ALEJANDRO",
    "curso": "9A",
    "puntos": 0
  },
  {
    "name": "MEJIA LUGO JUAN ESTEBAN",
    "curso": "9A",
    "puntos": 0
  },
  {
    "name": "MENDOZA CARDENAS VALENTINA",
    "curso": "9A",
    "puntos": 0
  },
  {
    "name": "MORENO ARIAS SARA LUCIA",
    "curso": "9A",
    "puntos": 0
  },
  {
    "name": "MORERA MARTINEZ DAMIAN ALEJANDRO",
    "curso": "9A",
    "puntos": 0
  },
  {
    "name": "OLAYA MARTINEZ MARCO ALEJANDRO",
    "curso": "9A",
    "puntos": 0
  },
  {
    "name": "ORTIZ URBINA VERONICA SOFIA",
    "curso": "9A",
    "puntos": 0
  },
  {
    "name": "OSPINA OJEDA SIMON",
    "curso": "9A",
    "puntos": 0
  },
  {
    "name": "PEÑA MEJÍA HEIPRY",
    "curso": "9A",
    "puntos": 0
  },
  {
    "name": "PLAZAS CUESTAS THOMAS JESUS",
    "curso": "9A",
    "puntos": 0
  },
  {
    "name": "RAMIREZ SIERRA TOMAS SANTIAGO",
    "curso": "9A",
    "puntos": 0
  },
  {
    "name": "RIOS FERIA ASHLEY MELISSA",
    "curso": "9A",
    "puntos": 0
  },
  {
    "name": "RUIZ RAMOS VALERIA ALEJANDRA",
    "curso": "9A",
    "puntos": 0
  },
  {
    "name": "SIMANCAS COLMENARES SAMUEL",
    "curso": "9A",
    "puntos": 0
  },
  {
    "name": "SOLANO SALAZAR SANTIAGO",
    "curso": "9A",
    "puntos": 0
  },
  {
    "name": "VARGAS PARRA DANNY ALEXANDER",
    "curso": "9A",
    "puntos": 0
  },
  {
    "name": "VASQUEZ MAYORGA ISABELLA",
    "curso": "9A",
    "puntos": 0
  },
  {
    "name": "VELEZ LEON JUAN SEBASTIAN",
    "curso": "9A",
    "puntos": 0
  },
  {
    "name": "VILLEGAS FIGUEROA DANA VALENTINA",
    "curso": "9A",
    "puntos": 0
  },
  {
    "name": "YOMAYUZA OBANDO CRISTIAN",
    "curso": "9A",
    "puntos": 0
  },
  {
    "name": "ASCANIO LAVADO VANESSA NICOLE",
    "curso": "9B",
    "puntos": 0
  },
  {
    "name": "BERRIO RAMIREZ ZARA",
    "curso": "9B",
    "puntos": 0
  },
  {
    "name": "CADENA CABRERA MARIA ALEJANDRA",
    "curso": "9B",
    "puntos": 0
  },
  {
    "name": "CASAS MARTINEZ DANA KAROLINA",
    "curso": "9B",
    "puntos": 0
  },
  {
    "name": "CASTELLANOS GARZON ADRIAN MAURICIO",
    "curso": "9B",
    "puntos": 0
  },
  {
    "name": "CHACON PATACON JUAN DAVID",
    "curso": "9B",
    "puntos": 0
  },
  {
    "name": "CHUQUEN HERNANDEZ SANTIAGO",
    "curso": "9B",
    "puntos": 0
  },
  {
    "name": "CONTRERAS GRANDA JUAN SEBASTIAN",
    "curso": "9B",
    "puntos": 0
  },
  {
    "name": "CRUZ DUARTE ARIADNA GABRIELA",
    "curso": "9B",
    "puntos": 0
  },
  {
    "name": "DIAZ CASTRO SOFIA",
    "curso": "9B",
    "puntos": 0
  },
  {
    "name": "DIAZ MONTAÑA MARIA PAULA",
    "curso": "9B",
    "puntos": 0
  },
  {
    "name": "FONSECA OROZCO ESTEFANIA",
    "curso": "9B",
    "puntos": 0
  },
  {
    "name": "FORERO GALVIS KAROL SAMANTHA",
    "curso": "9B",
    "puntos": 0
  },
  {
    "name": "GARCIA VANEGAS LIZETH JULIANA",
    "curso": "9B",
    "puntos": 0
  },
  {
    "name": "GUZMAN SANCHEZ ISABELLA",
    "curso": "9B",
    "puntos": 0
  },
  {
    "name": "HERNANDEZ MURILLO SANTIAGO",
    "curso": "9B",
    "puntos": 0
  },
  {
    "name": "MANCIPE MARTIN MARIANA",
    "curso": "9B",
    "puntos": 0
  },
  {
    "name": "MARQUEZ MENDEZ MARIANA",
    "curso": "9B",
    "puntos": 0
  },
  {
    "name": "MOLINA GUZMAN ANDRES MATEO",
    "curso": "9B",
    "puntos": 0
  },
  {
    "name": "MORALES TENJO EMILY",
    "curso": "9B",
    "puntos": 0
  },
  {
    "name": "MURILLO RUSSI DANIEL",
    "curso": "9B",
    "puntos": 0
  },
  {
    "name": "NAVAS PADILLA TOMAS ADOLFO",
    "curso": "9B",
    "puntos": 0
  },
  {
    "name": "PAEZ CARO NICOLAS",
    "curso": "9B",
    "puntos": 0
  },
  {
    "name": "PEREZ BELTRAN MIGUEL ANGEL",
    "curso": "9B",
    "puntos": 0
  },
  {
    "name": "PINTO CLAVIJO JUANA VALERIA",
    "curso": "9B",
    "puntos": 0
  },
  {
    "name": "RICO AVILA JUAN DAVID",
    "curso": "9B",
    "puntos": 0
  },
  {
    "name": "RUIZ PEREZ VALERIA",
    "curso": "9B",
    "puntos": 0
  },
  {
    "name": "RUIZ VARGAS VALENTINA",
    "curso": "9B",
    "puntos": 0
  },
  {
    "name": "SOLER CAÑON CARLOS MARIO",
    "curso": "9B",
    "puntos": 0
  },
  {
    "name": "TAPIAS AGUIRRE GABRIELA DEL ROCIO",
    "curso": "9B",
    "puntos": 0
  },
  {
    "name": "VALERO UZCATEGUI VANESSA JOPSELIN",
    "curso": "9B",
    "puntos": 0
  },
  {
    "name": "VIZCAYA LONDOÑO JEAN LOUP",
    "curso": "9B",
    "puntos": 0
  },
  {
    "name": "AGUILERA PADILLA JUAN JOSE",
    "curso": "10A",
    "puntos": 0
  },
  {
    "name": "BERNAL PINZON LAURA SOFIA",
    "curso": "10A",
    "puntos": 0
  },
  {
    "name": "BONILLA MENDOZA DAVID SANTIAGO",
    "curso": "10A",
    "puntos": 0
  },
  {
    "name": "CAMARGO CASTAÑO EMMANUEL",
    "curso": "10A",
    "puntos": 0
  },
  {
    "name": "CARDENAS ORJUELA DANNA GABRIELA",
    "curso": "10A",
    "puntos": 0
  },
  {
    "name": "CASTELLANOS BUITRAGO DANNA VALERIA",
    "curso": "10A",
    "puntos": 0
  },
  {
    "name": "CORREDOR SUAREZ LUNA ISABELLA",
    "curso": "10A",
    "puntos": 0
  },
  {
    "name": "CORTES CARDENAS JUAN SEBASTIAN",
    "curso": "10A",
    "puntos": 0
  },
  {
    "name": "DE LA PAVA CHAPARRO JUAN FELIPE",
    "curso": "10A",
    "puntos": 0
  },
  {
    "name": "DIAZ PEÑUELA JULIANA",
    "curso": "10A",
    "puntos": 0
  },
  {
    "name": "GARCIA FONSECA SARA VALENTINA",
    "curso": "10A",
    "puntos": 0
  },
  {
    "name": "GARZON CUECA ANDRES FELIPE",
    "curso": "10A",
    "puntos": 0
  },
  {
    "name": "GAVIRIA OROZCO ALEJANDRO",
    "curso": "10A",
    "puntos": 0
  },
  {
    "name": "GONZALEZ CAMARGO CESAR DAVID",
    "curso": "10A",
    "puntos": 0
  },
  {
    "name": "HERMIDA CASTIBLANCO SEBASTIAN",
    "curso": "10A",
    "puntos": 0
  },
  {
    "name": "HERRERA RODRIGUEZ MARIA FERNANDA",
    "curso": "10A",
    "puntos": 0
  },
  {
    "name": "MALDONADO CAMACHO SANTIAGO",
    "curso": "10A",
    "puntos": 0
  },
  {
    "name": "MARTIN PIÑEROS NIKOL VALERIA",
    "curso": "10A",
    "puntos": 0
  },
  {
    "name": "MARTINEZ MELENDEZ LEONARD SIMON",
    "curso": "10A",
    "puntos": 0
  },
  {
    "name": "MONTES BUITRAGO VALERIA",
    "curso": "10A",
    "puntos": 0
  },
  {
    "name": "MORENO NIÑO SAMUEL JERONIMO",
    "curso": "10A",
    "puntos": 0
  },
  {
    "name": "MORENO ROMERO JUAN PABLO",
    "curso": "10A",
    "puntos": 0
  },
  {
    "name": "NIÑO GUTIERREZ ALICE VALENTINA",
    "curso": "10A",
    "puntos": 0
  },
  {
    "name": "RAYO LOPEZ VALERIE YULIANA",
    "curso": "10A",
    "puntos": 0
  },
  {
    "name": "REYES ACOSTA VALERIE",
    "curso": "10A",
    "puntos": 0
  },
  {
    "name": "SALAZAR CAMACHO JUAN CARLOS",
    "curso": "10A",
    "puntos": 0
  },
  {
    "name": "SANCHEZ ALFONSO JULIAN DAVID",
    "curso": "10A",
    "puntos": 0
  },
  {
    "name": "URQUIJO MENDEZ SARA",
    "curso": "10A",
    "puntos": 0
  },
  {
    "name": "VARGAS GONZALEZ ANA SOFIA",
    "curso": "10A",
    "puntos": 0
  },
  {
    "name": "VILLALOBOS SUAREZ MARIA PAULA",
    "curso": "10A",
    "puntos": 0
  },
  {
    "name": "ATEHORTUA VILLA SEBASTIAN",
    "curso": "10B",
    "puntos": 0
  },
  {
    "name": "BELTRAN MAYORGA GABRIEL ESTEBAN",
    "curso": "10B",
    "puntos": 0
  },
  {
    "name": "CARREÑO GRACIA SIMON ESTEBAN",
    "curso": "10B",
    "puntos": 0
  },
  {
    "name": "CHAPARRO ACEVEDO JUAN DAVID",
    "curso": "10B",
    "puntos": 0
  },
  {
    "name": "CHAVES VALBUENA NATALIA MICHELL",
    "curso": "10B",
    "puntos": 0
  },
  {
    "name": "CIFUENTES CRUZ ANA SOFIA",
    "curso": "10B",
    "puntos": 0
  },
  {
    "name": "CLAVIJO RODRIGUEZ DOMINIC ESTEBAN",
    "curso": "10B",
    "puntos": 0
  },
  {
    "name": "CONTRERAS MONTAÑA JULIAN DAVID",
    "curso": "10B",
    "puntos": 0
  },
  {
    "name": "FLOREZ CASTAÑEDA VALENTINA",
    "curso": "10B",
    "puntos": 0
  },
  {
    "name": "GARZON BARAJAS MICHELLE SOFIA",
    "curso": "10B",
    "puntos": 0
  },
  {
    "name": "GAYOZO GARAY SAMUEL DAVID",
    "curso": "10B",
    "puntos": 0
  },
  {
    "name": "HERNANDEZ BRICEÑO SARA SOFIA",
    "curso": "10B",
    "puntos": 0
  },
  {
    "name": "JIMENEZ BALLESTEROS EMANUEL DAVID",
    "curso": "10B",
    "puntos": 0
  },
  {
    "name": "LEMOS RESTREPO JUAN ALEJANDRO",
    "curso": "10B",
    "puntos": 0
  },
  {
    "name": "LOZANO OBANDO SERGIO ALEJANDRO",
    "curso": "10B",
    "puntos": 0
  },
  {
    "name": "LUIS CASTIBLANCO JUAN PABLO",
    "curso": "10B",
    "puntos": 0
  },
  {
    "name": "MARTINEZ SANTANA LUIS FELIPE",
    "curso": "10B",
    "puntos": 0
  },
  {
    "name": "MEJIA HERNANDEZ ERICK ALEJANDRO",
    "curso": "10B",
    "puntos": 0
  },
  {
    "name": "PALMEZANO MARENGO NASHALIE MILENA",
    "curso": "10B",
    "puntos": 0
  },
  {
    "name": "PARRA CANTOR MARIA PAULA",
    "curso": "10B",
    "puntos": 0
  },
  {
    "name": "PARRA MORALES MARIAJOSE",
    "curso": "10B",
    "puntos": 0
  },
  {
    "name": "RAMIREZ SALAZAR JUAN DIEGO",
    "curso": "10B",
    "puntos": 0
  },
  {
    "name": "REYES NIÑO SARA SOFIA",
    "curso": "10B",
    "puntos": 0
  },
  {
    "name": "RIVERA GARCIA SOFIA",
    "curso": "10B",
    "puntos": 0
  },
  {
    "name": "RODRIGUEZ MENDIGAÑA ISABELLA",
    "curso": "10B",
    "puntos": 0
  },
  {
    "name": "ROMERO CORTES NICOLAS DAVID",
    "curso": "10B",
    "puntos": 0
  },
  {
    "name": "SANCHEZ LEON CARLOS SANTIAGO",
    "curso": "10B",
    "puntos": 0
  },
  {
    "name": "SOLER MARTIN AHYLIN",
    "curso": "10B",
    "puntos": 0
  },
  {
    "name": "AGUDELO GIRALDO DANILO",
    "curso": "10C",
    "puntos": 0
  },
  {
    "name": "AREVALO CALVO TOMAS",
    "curso": "10C",
    "puntos": 0
  },
  {
    "name": "AVENDAÑO APONTE JUAN PABLO",
    "curso": "10C",
    "puntos": 0
  },
  {
    "name": "BARBOSA SANDOVAL JULIANA",
    "curso": "10C",
    "puntos": 0
  },
  {
    "name": "BERMUDEZ ROBLES FELIPE",
    "curso": "10C",
    "puntos": 0
  },
  {
    "name": "BETANCOURT QUIÑONES JUAN JOSE",
    "curso": "10C",
    "puntos": 0
  },
  {
    "name": "BRITTO VARGAS SARA LUCIA",
    "curso": "10C",
    "puntos": 0
  },
  {
    "name": "CASTILLA GOMEZ ZARA",
    "curso": "10C",
    "puntos": 0
  },
  {
    "name": "DIAZ RAYO SAMUEL",
    "curso": "10C",
    "puntos": 0
  },
  {
    "name": "ESPINOSA ROMERO ALEJANDRO",
    "curso": "10C",
    "puntos": 0
  },
  {
    "name": "GARCES ARDILA SAMUEL ALEJANDRO",
    "curso": "10C",
    "puntos": 0
  },
  {
    "name": "GARZON BARRERO DANNA SOFIA",
    "curso": "10C",
    "puntos": 0
  },
  {
    "name": "GORDILLO CRUZ JUAN PABLO",
    "curso": "10C",
    "puntos": 0
  },
  {
    "name": "MENDEZ MUÑOZ MANUELA",
    "curso": "10C",
    "puntos": 0
  },
  {
    "name": "MUÑOZ AVILES JORGE ALBERTO",
    "curso": "10C",
    "puntos": 0
  },
  {
    "name": "MUÑOZ MESA SAMUEL",
    "curso": "10C",
    "puntos": 0
  },
  {
    "name": "PEÑA GUIO JUAN ESTEBAN",
    "curso": "10C",
    "puntos": 0
  },
  {
    "name": "PEREZ SARMIENTO ERIK SEBASTIAN",
    "curso": "10C",
    "puntos": 0
  },
  {
    "name": "PRECIADO HERRERA MICHELLE VALENTINA",
    "curso": "10C",
    "puntos": 0
  },
  {
    "name": "PULIDO CHAVARRO ISABELLA",
    "curso": "10C",
    "puntos": 0
  },
  {
    "name": "QUINTERO CEPEDA KAROL TATIANA",
    "curso": "10C",
    "puntos": 0
  },
  {
    "name": "QUINTERO CEPEDA LIZETH MARIANA",
    "curso": "10C",
    "puntos": 0
  },
  {
    "name": "RINCON RODRIGUEZ ALEJANDRA",
    "curso": "10C",
    "puntos": 0
  },
  {
    "name": "ROMERO CRUZ MARIA JOSE",
    "curso": "10C",
    "puntos": 0
  },
  {
    "name": "ROZO LEMA SANTIAGO",
    "curso": "10C",
    "puntos": 0
  },
  {
    "name": "SALGAR ZAMBRANO SAMUEL",
    "curso": "10C",
    "puntos": 0
  },
  {
    "name": "SANCHEZ QUINTERO ISABEL SOFIA",
    "curso": "10C",
    "puntos": 0
  },
  {
    "name": "SANDOVAL MORENO ANA MARIA",
    "curso": "10C",
    "puntos": 0
  },
  {
    "name": "SEGOVIA PAVA SARA",
    "curso": "10C",
    "puntos": 0
  },
  {
    "name": "TOVAR MALAGON DANNA LUJAN",
    "curso": "10C",
    "puntos": 0
  },
  {
    "name": "ULLOA GIRALDO JUAN PABLO",
    "curso": "10C",
    "puntos": 0
  },
  {
    "name": "ACUÑA BURGOS MIGUEL ANGEL",
    "curso": "11A",
    "puntos": 0
  },
  {
    "name": "AGUDELO IBAÑEZ JUAN DIEGO",
    "curso": "11A",
    "puntos": 0
  },
  {
    "name": "ALVAREZ VILLARREAL MARIA ALEJANDRA",
    "curso": "11A",
    "puntos": 0
  },
  {
    "name": "BECERRA URREGO DINA SELLENIC",
    "curso": "11A",
    "puntos": 0
  },
  {
    "name": "CABALLERO SOTO JANJERCY SLER",
    "curso": "11A",
    "puntos": 0
  },
  {
    "name": "CAMACHO URBINA WILLIAM ANDRES",
    "curso": "11A",
    "puntos": 0
  },
  {
    "name": "CAÑON GARZON MATEO",
    "curso": "11A",
    "puntos": 0
  },
  {
    "name": "CASTAÑEDA MERCHAN MARIA JOSE",
    "curso": "11A",
    "puntos": 0
  },
  {
    "name": "CRUZ NEIRA ANDRES MANUEL",
    "curso": "11A",
    "puntos": 0
  },
  {
    "name": "CUBIDES GOMEZ SANTIAGO",
    "curso": "11A",
    "puntos": 0
  },
  {
    "name": "CUBIDES VELASQUEZ DAVID FELIPE",
    "curso": "11A",
    "puntos": 0
  },
  {
    "name": "FOX MORALES LAURA SOFIA",
    "curso": "11A",
    "puntos": 0
  },
  {
    "name": "GAVILAN CHAVES JUAN ESTEBAN",
    "curso": "11A",
    "puntos": 0
  },
  {
    "name": "GOMEZ JOYA FABIAN CAMILO",
    "curso": "11A",
    "puntos": 0
  },
  {
    "name": "GRACIA ALFONSO JUANA ISABELLA",
    "curso": "11A",
    "puntos": 0
  },
  {
    "name": "GUALDRON GALVIS NICOLAS DAVID",
    "curso": "11A",
    "puntos": 0
  },
  {
    "name": "GUALDRON ORJUELA LAURA SOFIA",
    "curso": "11A",
    "puntos": 0
  },
  {
    "name": "LARROTTA BARRERA JUAN SEBASTIAN",
    "curso": "11A",
    "puntos": 0
  },
  {
    "name": "LEON JARA JUAN ESTEBAN",
    "curso": "11A",
    "puntos": 0
  },
  {
    "name": "LOZANO BELTRAN ANGELA TATIANA",
    "curso": "11A",
    "puntos": 0
  },
  {
    "name": "LUNA SEGURA JUAN SEBASTIAN",
    "curso": "11A",
    "puntos": 0
  },
  {
    "name": "MARTINEZ BURBANO JULIAN ESTEBAN",
    "curso": "11A",
    "puntos": 0
  },
  {
    "name": "MOLINA ZUÑIGA LUCIANA",
    "curso": "11A",
    "puntos": 0
  },
  {
    "name": "MONROY GUZMAN NICOLE STEFANNY",
    "curso": "11A",
    "puntos": 0
  },
  {
    "name": "MORENO BAUTISTA JULIANA",
    "curso": "11A",
    "puntos": 0
  },
  {
    "name": "MUÑOZ VARGAS SANTIAGO",
    "curso": "11A",
    "puntos": 0
  },
  {
    "name": "ORDOÑEZ SALAMANCA MARIANA SOFIA",
    "curso": "11A",
    "puntos": 0
  },
  {
    "name": "QUINTERO PACHON ANDRES FELIPE",
    "curso": "11A",
    "puntos": 0
  },
  {
    "name": "RAMIREZ AVILA MICHEL VALENTINA",
    "curso": "11A",
    "puntos": 0
  },
  {
    "name": "RIVERA CLAVIJO SHARA",
    "curso": "11A",
    "puntos": 0
  },
  {
    "name": "ROA CHACON JOEL JULIAN",
    "curso": "11A",
    "puntos": 0
  },
  {
    "name": "RODRIGUEZ ARIAS NATALIA",
    "curso": "11A",
    "puntos": 0
  },
  {
    "name": "SABOGAL REYES JUAN EMANUEL",
    "curso": "11A",
    "puntos": 0
  },
  {
    "name": "SILVA LOZANO MARIANA",
    "curso": "11A",
    "puntos": 0
  },
  {
    "name": "TORRES RAMIREZ JUAN CAMILO",
    "curso": "11A",
    "puntos": 0
  },
  {
    "name": "URIBE CARDONA SEBASTIAN",
    "curso": "11A",
    "puntos": 0
  },
  {
    "name": "VALLARINO VELASQUEZ SANTIAGO",
    "curso": "11A",
    "puntos": 0
  },
  {
    "name": "VILLAMIZAR DUARTE MARIA CAMILA",
    "curso": "11A",
    "puntos": 0
  },
  {
    "name": "ACOSTA ALARCON JUAN ANDRES",
    "curso": "11B",
    "puntos": 0
  },
  {
    "name": "AGUDELO GARCIA DEREK SANTIAGO",
    "curso": "11B",
    "puntos": 0
  },
  {
    "name": "AGUDELO GONZALEZ DAVID",
    "curso": "11B",
    "puntos": 0
  },
  {
    "name": "ALDANA TORRES JOSE DANIEL",
    "curso": "11B",
    "puntos": 0
  },
  {
    "name": "ALVAREZ CIFUENTES SARA SOFIA",
    "curso": "11B",
    "puntos": 0
  },
  {
    "name": "ANGEL FABREGAS MARIANA",
    "curso": "11B",
    "puntos": 0
  },
  {
    "name": "ARIAS MARTINEZ SEBASTIAN",
    "curso": "11B",
    "puntos": 0
  },
  {
    "name": "BARRERA RODRIGUEZ SARA CATALINA",
    "curso": "11B",
    "puntos": 0
  },
  {
    "name": "BARRETO POSADA MARTIN ESTEBAN",
    "curso": "11B",
    "puntos": 0
  },
  {
    "name": "BRAVO GARZON MARIA JOSE",
    "curso": "11B",
    "puntos": 0
  },
  {
    "name": "BUENO HERNANDEZ JUAN CAMILO",
    "curso": "11B",
    "puntos": 0
  },
  {
    "name": "CHUQUEN HERNANDEZ VALENTINA",
    "curso": "11B",
    "puntos": 0
  },
  {
    "name": "CUBIDES FORERO SARA",
    "curso": "11B",
    "puntos": 0
  },
  {
    "name": "DIAZ MARQUEZ JUAN ANDRES",
    "curso": "11B",
    "puntos": 0
  },
  {
    "name": "ESQUIVEL DIAZ LAURA MARCELA",
    "curso": "11B",
    "puntos": 0
  },
  {
    "name": "FARFAN CASTRO ANGEL DAVID",
    "curso": "11B",
    "puntos": 0
  },
  {
    "name": "FRANCO MESA SARAH",
    "curso": "11B",
    "puntos": 0
  },
  {
    "name": "GALINDO VELASQUEZ DANIEL SANTIAGO",
    "curso": "11B",
    "puntos": 0
  },
  {
    "name": "GOMEZ PINILLA CHRISTOPHER JULIAN",
    "curso": "11B",
    "puntos": 0
  },
  {
    "name": "GUERRERO SALAMANCA JUAN MANUEL",
    "curso": "11B",
    "puntos": 0
  },
  {
    "name": "LOPEZ PINILLA JUAN CAMILO",
    "curso": "11B",
    "puntos": 0
  },
  {
    "name": "MALPICA SANCHEZ MARIA FERNANDA",
    "curso": "11B",
    "puntos": 0
  },
  {
    "name": "MARTINEZ QUIROGA ESTEBAN",
    "curso": "11B",
    "puntos": 0
  },
  {
    "name": "MORENO PINZON NICOLAS",
    "curso": "11B",
    "puntos": 0
  },
  {
    "name": "MURCIA ANGULO DANIELA",
    "curso": "11B",
    "puntos": 0
  },
  {
    "name": "PACHON PINEDA NICOLAS",
    "curso": "11B",
    "puntos": 0
  },
  {
    "name": "PARRA ACEVEDO ESTEBAN",
    "curso": "11B",
    "puntos": 0
  },
  {
    "name": "RINCON RUIZ SAMUEL",
    "curso": "11B",
    "puntos": 0
  },
  {
    "name": "RIVEROS GARCIA MARIA JOSE",
    "curso": "11B",
    "puntos": 0
  },
  {
    "name": "RODRIGUEZ CORREDOR SOFIA",
    "curso": "11B",
    "puntos": 0
  },
  {
    "name": "SARMIENTO MEDINA JULIAN CAMILO",
    "curso": "11B",
    "puntos": 0
  },
  {
    "name": "SILVA GALEANO ANGIE TATIANA",
    "curso": "11B",
    "puntos": 0
  },
  {
    "name": "TAMAYO CARRILLO MARIA FERNANDA",
    "curso": "11B",
    "puntos": 0
  },
  {
    "name": "VERDOOREN ROSERO SIMON",
    "curso": "11B",
    "puntos": 0
  },
  {
    "name": "VILLAMIL RICO WILMER JOEL",
    "curso": "11B",
    "puntos": 0
  },
  {
    "name": "ZURITA RUIZ MARIA JOSE",
    "curso": "11B",
    "puntos": 0
  },
  {
    "name": "ARES",
    "curso": "0",
    "puntos": 0
  },
  {
    "name": "REA",
    "curso": "0",
    "puntos": 0
  },
  {
    "name": "HEFESTO",
    "curso": "0",
    "puntos": 0
  },
  {
    "name": "NIKE",
    "curso": "0",
    "puntos": 0
  },
  {
    "name": "APOLO",
    "curso": "0",
    "puntos": 0
  },
  {
    "name": "NIX",
    "curso": "0",
    "puntos": 0
  },
  {
    "name": "ARTEMISA",
    "curso": "0",
    "puntos": 0
  },
  {
    "name": "ATENEA",
    "curso": "0",
    "puntos": 0
  },
  {
    "name": "PERSEFONE",
    "curso": "0",
    "puntos": 0
  },
  {
    "name": "HERCULES",
    "curso": "0",
    "puntos": 0
  },
  {
    "name": "DEMETER",
    "curso": "0",
    "puntos": 0
  },
  {
    "name": "HADES",
    "curso": "0",
    "puntos": 0
  },
  {
    "name": "HELIOS",
    "curso": "0",
    "puntos": 0
  },
  {
    "name": "CRONOS",
    "curso": "0",
    "puntos": 0
  },
  {
    "name": "HESTIA",
    "curso": "0",
    "puntos": 0
  },
  {
    "name": "GEA",
    "curso": "0",
    "puntos": 0
  },
  {
    "name": "POSEIDON",
    "curso": "0",
    "puntos": 0
  },
  {
    "name": "HERA",
    "curso": "0",
    "puntos": 0
  },
  {
    "name": "METIS",
    "curso": "0",
    "puntos": 0
  },
  {
    "name": "CLOTO",
    "curso": "0",
    "puntos": 0
  },
  {
    "name": "LAQUESIS",
    "curso": "0",
    "puntos": 0
  },
  {
    "name": "ATROPOS",
    "curso": "0",
    "puntos": 0
  },
  {
    "name": "PROMETEO",
    "curso": "0",
    "puntos": 0
  }
]